{
  "createdId": "QxHw5Pv1DT_1_X7__Kl_n",
  "id": "kakie-banki-oplachivayut-invois-v-koreyu",
  "versionId": "PauqT4Gk0hPmpWatQIJfW",
  "createdAt": "2025-06-11T07:20:32.947Z",
  "updatedAt": "2025-07-31T10:11:13.852Z",
  "publishedAt": "2025-06-11T07:20:32.947Z",
  "readonly": true,
  "data": {
    "CEO": {
      "title": "Какие банки оплачивают инвойс в Корею: обзор надежных платежных решений | ВЭД-Мастер",
      "description": "Обзор банков, поддерживающих оплату инвойсов в Корею, с учетом комиссий, сроков и особенностей международных переводов. Рекомендации от ВЭД-Мастер для безопасных расчетов."
    },
    "title": "Какие банки оплачивают инвойс в Корею: выбор лучшего банка для международных расчётов",
    "author": "karelin-maxim",
    "visible": false,
    "markdown": "# Какие банки оплачивают инвойс в Корею: выбор лучшего банка для международных расчётов\n\nВыбор правильного банка для оплаты инвойсов в Южную Корею играет ключевую роль в успешном ведении бизнеса. Южная Корея, как одна из ведущих экономик Азии, требует особого внимания к деталям в финансовых операциях. Правильный банк обеспечивает:\n\n* Надёжность и безопасность: Защита от мошенничества и ошибок в транзакциях.  \n* Скорость переводов: Быстрые и своевременные платежи помогают поддерживать хорошие отношения с корейскими партнёрами.  \n* Выгодные условия: Конкурентоспособные комиссии и курсы обмена валют снижают общие затраты на сделки.\n\n## Как международные расчёты влияют на бизнес-процессы и торговые отношения?\n\nМеждународные расчёты оказывают значительное влияние на бизнес-процессы и торговые отношения:\n\n* Кэш-флоу: Задержки в платежах могут нарушить финансовые потоки и повлиять на ликвидность компании. \n* Репутация: Надёжные и своевременные расчёты укрепляют доверие между партнёрами и улучшают деловую репутацию.  \n* Валютные риски: Колебания валютных курсов могут повлиять на стоимость сделок, поэтому важно управлять этими рисками.\n\n## О чём пойдёт речь в статье:\n\nСтатья будет посвящена тому, как выбрать банк для расчётов с корейскими партнёрами, чтобы минимизировать риски и затраты. Мы рассмотрим:\n\n* Критерии выбора банка: Надёжность, скорость, комиссии и валютные условия.  \n* Оптимизация платёжных процессов: Внедрение автоматизации и использование современных платёжных систем.  \n* Управление рисками: Стратегии для минимизации валютных и транзакционных рисков.\n\nЭти аспекты помогут компаниям эффективно управлять международными расчётами и укреплять торговые отношения с партнёрами в Южной Корее.\n\nC2A: ВЭД-Мастер|Не выбрали банк? Начните оплату инвойса здесь|/import/oplata-invoice|Оплатить инвойс в Корею \n\n## Корейские банки с международными расчетами\n\nЮжная Корея, будучи одной из ведущих экономик Азии, предлагает широкий выбор банков для международных переводов и расчётов по инвойсам. Рассмотрим, какие банки обеспечивают эти услуги и как выбрать подходящий банк для ваших нужд.\n\n## Какие банки в Южной Корее обеспечивают международные переводы и расчёт по инвойсам?\n\n### Woori Bank\n\nWoori Bank — один из крупнейших банков в Южной Корее, предлагающий обширные услуги для международных расчётов. Банк известен своей надёжностью и конкурентоспособными условиями для бизнеса.\n\n### Kookmin Bank\n\nKookmin Bank предоставляет широкий спектр услуг для международных переводов, включая выгодные условия по комиссиям и курсам обмена валют. Банк активно поддерживает малый и средний бизнес в международной торговле.\n\n## Как выбрать корейский банк для перевода средств и оплаты инвойса?\n\n* Репутация и надёжность: Выбирайте банки с хорошей репутацией и опытом в международных операциях.  \n* Комиссии и курсы обмена: Сравните условия по комиссиям и валютным курсам, чтобы минимизировать затраты.  \n* Качество обслуживания: Убедитесь, что банк предоставляет качественную поддержку и консультации по международным вопросам.\n\n## Какие дополнительные услуги предоставляют эти банки для международных расчётов?\n\nКорейские банки предлагают дополнительные услуги, такие как управление валютными рисками, консультации по международной торговле и специализированные решения для бизнеса, работающего на глобальном рынке.\n\nC2A: ВЭД-Мастер|Не выбрали банк? Начните оплату инвойса здесь|/import/oplata-invoice|Оплатить инвойс в Корею \n\n## Международные банки с филиалами в Корее\n\nКакие международные банки имеют филиалы в Южной Корее и предлагают расчёты с корейскими контрагентами?\n\nHSBC, CitiBank, Standard Chartered\n\nЭти международные банки имеют филиалы в Южной Корее и предлагают широкий спектр услуг для расчётов с корейскими контрагентами. Они обеспечивают надёжность и удобство для компаний, работающих на международном уровне.\n\n## Как выбрать международный банк для оплаты инвойса, если вы не хотите работать с корейскими банками напрямую?\n\n* Глобальное присутствие: Выбирайте банки с широкой международной сетью, что обеспечивает лёгкий доступ к услугам в разных странах.  \n* Условия и комиссии: Сравните условия по комиссиям и курсам обмена, чтобы выбрать наиболее выгодный вариант.  \n* Качество обслуживания: Убедитесь, что банк предоставляет качественную поддержку и консультации по международным вопросам.\n\n## Птёжные системы и альтернативные банки\n\n### Какие международные платёжные системы поддерживают расчёты с Кореей?\n\nPayPal, TransferWise\n\nЭти платёжные системы предлагают удобные решения для международных расчётов с Кореей, обеспечивая быстрые и безопасные переводы.\n\n## Какую роль играют платёжные системы в ускорении расчётов с корейскими партнёрами?\n\nПлатёжные системы позволяют значительно ускорить процесс расчётов, обеспечивая мгновенные переводы и снижая затраты на комиссии. Они предоставляют удобные инструменты для управления финансами и позволяют компаниям оперативно реагировать на изменения в бизнес-среде.  \n\nЭти аспекты делают выбор правильного банка или платёжной системы важным шагом для успешного ведения бизнеса с корейскими партнёрами, обеспечивая надёжность и эффективность финансовых операций.\n\n## Комиссии и затраты при международных переводах в Корею\n\nМеждународные переводы в Южную Корею могут сопровождаться различными комиссиями и сборами, которые важно учитывать для оптимизации затрат. Рассмотрим, как они рассчитываются и как выбрать банк с минимальными комиссиями.\n\nC2A: ВЭД-Мастер|Не выбрали банк? Начните оплату инвойса здесь|/import/oplata-invoice|Оплатить инвойс в Корею \n\n## Как рассчитываются комиссии за переводы в Южную Корею?\n\nКомиссии за международные переводы обычно зависят от нескольких факторов:\n\n1. Сумма перевода: Многие банки устанавливают процентную ставку от суммы перевода или фиксированную плату.  \n2. Тип перевода: Комиссии могут различаться в зависимости от срочности перевода и используемого канала (например, SWIFT).  \n3. Банк-получатель: Некоторые банки взимают дополнительные сборы за обработку входящих международных переводов.\n\n## Какие дополнительные сборы могут возникнуть при конвертации валюты?\n\nПри конвертации валюты могут возникнуть следующие дополнительные сборы:\n\n1. Спред валютного курса: Разница между курсом покупки и продажи валюты, которую банк использует для получения прибыли.  \n2. Комиссия за конвертацию: Некоторые банки взимают дополнительную плату за обмен валюты, особенно если это происходит в рамках международного перевода.\n\n## Как выбрать банк с минимальными комиссиями для международных расчетов?\n\n1. Сравнение условий: Исследуйте предложения различных банков и платёжных систем, чтобы найти наиболее выгодные условия по комиссиям и курсам обмена.  \n2. Пакетные предложения: Некоторые банки предлагают специальные тарифы для бизнеса, которые могут включать сниженные комиссии за международные переводы.  \n3. Отзывы и репутация: Изучите отзывы клиентов и репутацию банка на рынке, чтобы убедиться в его надёжности и прозрачности условий.\n\nВыбор правильного банка или платёжной системы с минимальными комиссиями поможет оптимизировать затраты на международные переводы и повысить эффективность финансовых операций с корейскими партнёрами.\n\n## Документы, необходимые для перевода инвойса в Корею\n\nВедение международных расчётов требует тщательной подготовки и соблюдения всех формальностей. При переводе инвойса в Южную Корею важно иметь под рукой все необходимые документы, чтобы избежать задержек и отказов. Давайте рассмотрим, какие документы требуются и как правильно их оформить.\n\n### Какие документы нужны для осуществления перевода и оплаты инвойса в Корею?\n\nДля успешного проведения международного перевода необходимо подготовить ряд ключевых документов. В первую очередь, это инвойс, который служит основным подтверждением сделки. Он должен содержать все важные детали, такие как сумма, валюта, описание товаров или услуг, и реквизиты обеих сторон. Помимо инвойса, может потребоваться контракт или договор, который подтверждает условия сделки, особенно для крупных транзакций. \n\nНе забудьте о банковских реквизитах, которые должны быть точными и полными, включая SWIFT/BIC код. Если речь идёт о товарной сделке, могут понадобиться документы на груз, такие как накладные или коносаменты. И, конечно, идентификационные документы для подтверждения личности отправителя и получателя, если это требуется банком.\n\n## Какие требования предъявляются к инвойсам при международных расчётах?\n\nИнвойс — это не просто документ, а важный инструмент в международных расчётах. Он должен быть составлен с особой тщательностью. Все данные в инвойсе должны быть точными и соответствовать условиям сделки. Язык инвойса, как правило, английский или согласованный с партнёром, а валюта должна быть чётко указана. Не забывайте о подписях и печатях — они подтверждают подлинность документа и его юридическую силу.\n\nC2A: ВЭД-Мастер|Не выбрали банк? Начните оплату инвойса здесь|/import/oplata-invoice|Оплатить инвойс в Корею  \n\n## Как избежать задержек или отказов при проведении транзакций в Южной Корее?\n\nЧтобы избежать неприятных сюрпризов в виде задержек или отказов, важно следовать нескольким простым рекомендациям. Во-первых, тщательно проверяйте банковские реквизиты и контактные данные получателя. \nВо-вторых, соблюдайте сроки отправки документов и платежей, чтобы не нарушать договорённости. Поддерживайте связь с вашим банком, чтобы оперативно решать возможные вопросы. И, наконец, ознакомьтесь с требованиями корейских банков и регулирующих органов, чтобы избежать несоответствий и обеспечить гладкое проведение международных расчётов.  \n\nЭти шаги помогут вам уверенно управлять международными переводами и минимизировать риски, связанные с финансовыми операциями в Южной Корее.\n\n## Риски при оплате инвойсов в Южную Корею и как их избежать\n\nМеждународные расчёты с Южной Кореей, как и с любой другой страной, сопряжены с определёнными рисками. Понимание этих рисков и знание способов их минимизации помогут вам успешно управлять финансовыми операциями и поддерживать стабильные деловые отношения.\n\n## Какие риски связаны с международными расчетами с Кореей?\n\n### Санкции и политическая нестабильность\n\nПолитическая ситуация может влиять на международные расчёты. Санкции или изменения в политике могут привести к задержкам или блокировке транзакций. Важно следить за международными новостями и быть в курсе текущих политических событий.\n\n### Валютные колебания\n\nКолебания валютных курсов могут существенно повлиять на стоимость сделок. Это особенно актуально для долгосрочных контрактов, где изменения курса могут привести к значительным финансовым потерям.\n\n## Как защититься от ошибок и недоразумений при переводах по инвойсам?\n\n1. Тщательная проверка документов: Убедитесь, что все данные в инвойсе и других документах точны и соответствуют условиям сделки.  \n2. Поддержка связи с банком: Регулярно общайтесь с вашим банком для оперативного решения возможных вопросов и уточнения деталей транзакций.  \n3. Использование надёжных платёжных систем: Выбирайте проверенные платёжные системы и банки с хорошей репутацией для проведения международных переводов.\n\nC2A: ВЭД-Мастер|Не выбрали банк? Начните оплату инвойса здесь|/import/oplata-invoice|Оплатить инвойс в Корею \n\n## Как избежать высоких комиссий при оплате инвойсов через международные банки?\n\n1. Сравнение условий: Исследуйте предложения различных банков и платёжных систем, чтобы найти наиболее выгодные условия по комиссиям и курсам обмена.  \n2. Пакетные предложения: Некоторые банки предлагают специальные тарифы для бизнеса, которые могут включать сниженные комиссии за международные переводы.  \n3. Переговоры с банком: Обсудите с вашим банком возможность снижения комиссий, особенно если вы планируете регулярные крупные переводы.\n\n## Заключение\n\nВыбор правильного банка для оплаты инвойсов в Южную Корею — это стратегическое решение, которое может существенно повлиять на успех вашего бизнеса. В условиях глобальной экономики, где скорость и надёжность финансовых операций играют ключевую роль, правильный выбор финансового партнёра становится критически важным.\n\n## Почему важно выбрать правильный банк для оплаты инвойсов в Южную Корею?\n\nПравильный банк обеспечивает не только безопасность и надёжность транзакций, но и оптимальные условия по комиссиям и валютным курсам. Это помогает минимизировать затраты и избежать задержек, что особенно важно для поддержания доверительных отношений с корейскими партнёрами.\n\nC2A: ВЭД-Мастер|Не выбрали банк? Начните оплату инвойса здесь|/import/oplata-invoice|Оплатить инвойс в Корею \n\n## Как выбрать оптимальные платёжные решения для международных расчётов с корейскими контрагентами?\n\nПри выборе платёжных решений важно учитывать несколько ключевых факторов:\n\n1. Репутация и надёжность: Выбирайте банки и платёжные системы с проверенной репутацией и опытом в международных операциях.  \n2. Комиссии и курсы обмена: Сравните условия по комиссиям и валютным курсам, чтобы выбрать наиболее выгодный вариант.  \n3. Качество обслуживания: Убедитесь, что ваш финансовый партнёр предоставляет качественную поддержку и консультации по международным вопросам.\n\n## Какие шаги помогут минимизировать комиссии и риски при расчётах с Южной Кореей?\n\n1. Сравнение предложений: Исследуйте различные предложения банков и платёжных систем, чтобы найти наиболее выгодные условия.  \n2. Автоматизация процессов: Внедрите системы автоматической обработки инвойсов и интеграции с платёжными платформами для повышения эффективности.  \n3. Регулярный мониторинг: Проводите регулярный анализ и мониторинг платёжных процессов для своевременного выявления и устранения проблем.\n\nЭти шаги помогут вам оптимизировать международные расчёты с Южной Кореей, минимизировать затраты и риски, а также обеспечить стабильность и эффективность ваших финансовых операций.  \n",
    "createdAt": "2025-06-11T07:20:32.947Z",
    "updatedAt": "2025-07-31T10:11:13.852Z",
    "coverImage": {
      "url": "https://cdn.ab.tech/99db672123021e36c347b5dff2ddf24d8650015d",
      "hash": "99db672123021e36c347b5dff2ddf24d8650015d",
      "size": 320458,
      "width": 1000,
      "fileId": "uc1Sa1Pn6QmaQSkBxZtru",
      "height": 667,
      "status": "uploaded",
      "fileName": "",
      "mimeType": "image/jpeg",
      "extension": "jpg"
    },
    "publishedAt": "2025-06-11T07:20:32.947Z",
    "previewImage": {
      "url": "https://cdn.ab.tech/81247c88ed0d9a0e48052c36869706066b005bd4",
      "hash": "81247c88ed0d9a0e48052c36869706066b005bd4",
      "size": 334740,
      "width": 1000,
      "fileId": "A9Fj3FxUCdBS655dRNz1X",
      "height": 667,
      "status": "uploaded",
      "fileName": "",
      "mimeType": "image/jpeg",
      "extension": "jpg"
    },
    "articleCategories": [
      "expert-opinion"
    ]
  }
}